leak_detect/__init__.py
leak_detect/base.py
leak_detect-0.0.1.dist-info/LICENSE
leak_detect-0.0.1.dist-info/METADATA
leak_detect-0.0.1.dist-info/WHEEL
leak_detect-0.0.1.dist-info/top_level.txt
leak_detect-0.0.1.dist-info/RECORD
