Metadata-Version: 2.1
Name: leak-detect
Version: 0.0.1
Summary: Detect leakage in ML datasets using complex numbers and NANs
Home-page: https://github.com/abhayspawar/leak-detect
Author: Abhay Pawar
Author-email: abhayspawar@gmail.com
License: UNKNOWN
Platform: UNKNOWN
Classifier: Programming Language :: Python :: 3
Classifier: Programming Language :: Python :: 2
Classifier: License :: OSI Approved :: MIT License
Classifier: Operating System :: OS Independent
Requires-Dist: pandas
Requires-Dist: numpy
